anubis/__init__.py
anubis/config.py
anubis/database.py
anubis/default.py
anubis/dependencies.py
anubis/main.py
anubis/rego.py
anubis/utils.py
anubis/version.py
anubis/wac.py
anubis/audit/__init__.py
anubis/audit/models.py
anubis/audit/operations.py
anubis/audit/routers.py
anubis/audit/schemas.py
anubis/middleware/__init__.py
anubis/middleware/operations.py
anubis/middleware/routers.py
anubis/middleware/schemas.py
anubis/policies/__init__.py
anubis/policies/models.py
anubis/policies/operations.py
anubis/policies/routers.py
anubis/policies/schemas.py
anubis/tenants/__init__.py
anubis/tenants/models.py
anubis/tenants/operations.py
anubis/tenants/routers.py
anubis/tenants/schemas.py
anubis/tests/__init__.py
anubis/tests/test_api.py
anubis/tests/test_audit.py
anubis/tests/test_policies.py
anubis/tests/test_rdf_parsing.py
anubis/tests/test_tenants.py
anubis/tests/utils.py
anubis_policy_api-0.6.0.dist-info/METADATA
anubis_policy_api-0.6.0.dist-info/WHEEL
anubis_policy_api-0.6.0.dist-info/top_level.txt
anubis_policy_api-0.6.0.dist-info/RECORD
